buckup/__init__.py
buckup/bucket_creator.py
buckup/command_line.py
buckup/exceptions.py
buckup/utils.py
buckup-0.2.dist-info/LICENSE
buckup-0.2.dist-info/METADATA
buckup-0.2.dist-info/WHEEL
buckup-0.2.dist-info/entry_points.txt
buckup-0.2.dist-info/top_level.txt
buckup-0.2.dist-info/RECORD
