Metadata-Version: 2.2
Name: buckup
Version: 0.2
Summary: Create S3 buckets in seconds from your command line to use on your website.
Home-page: https://github.com/torchbox/buckup
Author: Tomasz Knapik
Author-email: tomasz.knapik@torchbox.com
Maintainer: Torchbox
Maintainer-email: info@torchbox.com
License: BSD 3-Clause License
Keywords: aws,s3,bucket,storage,cloud
Classifier: License :: OSI Approved
Classifier: License :: OSI Approved :: BSD License
Classifier: Development Status :: 5 - Production/Stable
Classifier: Environment :: Console
Classifier: Topic :: Utilities
Classifier: Topic :: System :: Systems Administration
Classifier: Programming Language :: Python :: 3 :: Only
Classifier: Intended Audience :: System Administrators
Classifier: Intended Audience :: Developers
Classifier: Operating System :: OS Independent
Classifier: Natural Language :: English
Requires-Python: >=3.4
License-File: LICENSE
Requires-Dist: boto3
